[
  {
    "id": 1,
    "label": "bullying",
    "scores": {
      "bullying": 0.9640000000000001,
      "non_bullying": 0.03599999999999992
    },
    "is_bullying": true,
    "timestamp": "2026-07-06T05:23:52.053585",
    "message": "If you show up in the class group again, I will make sure everyone turns against you.",
    "category": "harassment",
    "category_label": "Harassment",
    "danger_level": "Critical",
    "confidence": 96.4,
    "danger_score": 96.4,
    "keywords": [
      "everyone",
      "turns",
      "against"
    ],
    "explanation": "Critical risk: the message shows direct harassment and coordinated intimidation toward a student.",
    "share_summary": "CyberGuard AI Analysis\nCategory: Harassment\nDanger Level: Critical\nConfidence: 96.4%\nFlagged Words: everyone, turns, against\nTimestamp: 06 Jul 2026, 05:23 AM\nExplanation: Critical risk: the message shows direct harassment and coordinated intimidation toward a student."
  },
  {
    "id": 2,
    "label": "bullying",
    "scores": {
      "bullying": 0.948,
      "non_bullying": 0.052000000000000046
    },
    "is_bullying": true,
    "timestamp": "2026-07-05T04:23:52.053585",
    "message": "People from your religion do not belong in our chat.",
    "category": "hate_speech",
    "category_label": "Hate Speech",
    "danger_level": "Critical",
    "confidence": 94.8,
    "danger_score": 94.8,
    "keywords": [
      "religion",
      "belong"
    ],
    "explanation": "Critical risk: the message targets identity and excludes someone based on religion.",
    "share_summary": "CyberGuard AI Analysis\nCategory: Hate Speech\nDanger Level: Critical\nConfidence: 94.8%\nFlagged Words: religion, belong\nTimestamp: 05 Jul 2026, 04:23 AM\nExplanation: Critical risk: the message targets identity and excludes someone based on religion."
  },
  {
    "id": 3,
    "label": "bullying",
    "scores": {
      "bullying": 0.892,
      "non_bullying": 0.10799999999999998
    },
    "is_bullying": true,
    "timestamp": "2026-07-04T03:23:52.053585",
    "message": "Keep talking and I will hurt you after school.",
    "category": "threat",
    "category_label": "Threat",
    "danger_level": "High",
    "confidence": 89.2,
    "danger_score": 89.2,
    "keywords": [
      "hurt",
      "after school"
    ],
    "explanation": "High risk: the message contains a direct threat of physical harm.",
    "share_summary": "CyberGuard AI Analysis\nCategory: Threat\nDanger Level: High\nConfidence: 89.2%\nFlagged Words: hurt, after school\nTimestamp: 04 Jul 2026, 03:23 AM\nExplanation: High risk: the message contains a direct threat of physical harm."
  },
  {
    "id": 4,
    "label": "bullying",
    "scores": {
      "bullying": 0.867,
      "non_bullying": 0.133
    },
    "is_bullying": true,
    "timestamp": "2026-07-03T02:23:52.053585",
    "message": "You are such a dumb loser, nobody wants your opinion.",
    "category": "insult",
    "category_label": "Insult",
    "danger_level": "High",
    "confidence": 86.7,
    "danger_score": 86.7,
    "keywords": [
      "dumb",
      "loser",
      "nobody"
    ],
    "explanation": "High risk: the message uses repeated personal insults and rejection language.",
    "share_summary": "CyberGuard AI Analysis\nCategory: Insult\nDanger Level: High\nConfidence: 86.7%\nFlagged Words: dumb, loser, nobody\nTimestamp: 03 Jul 2026, 02:23 AM\nExplanation: High risk: the message uses repeated personal insults and rejection language."
  },
  {
    "id": 5,
    "label": "bullying",
    "scores": {
      "bullying": 0.735,
      "non_bullying": 0.265
    },
    "is_bullying": true,
    "timestamp": "2026-07-02T01:23:52.053585",
    "message": "Do not invite her to the project chat. She does not fit with us.",
    "category": "exclusion",
    "category_label": "Exclusion",
    "danger_level": "Medium",
    "confidence": 73.5,
    "danger_score": 73.5,
    "keywords": [
      "invite",
      "fit"
    ],
    "explanation": "Medium risk: the message encourages exclusion from a shared school activity.",
    "share_summary": "CyberGuard AI Analysis\nCategory: Exclusion\nDanger Level: Medium\nConfidence: 73.5%\nFlagged Words: invite, fit\nTimestamp: 02 Jul 2026, 01:23 AM\nExplanation: Medium risk: the message encourages exclusion from a shared school activity."
  },
  {
    "id": 6,
    "label": "bullying",
    "scores": {
      "bullying": 0.6809999999999999,
      "non_bullying": 0.31900000000000006
    },
    "is_bullying": true,
    "timestamp": "2026-07-01T00:23:52.053585",
    "message": "Your post was embarrassing and everyone probably laughed at it.",
    "category": "harassment",
    "category_label": "Harassment",
    "danger_level": "Medium",
    "confidence": 68.1,
    "danger_score": 68.1,
    "keywords": [
      "embarrassing",
      "laughed"
    ],
    "explanation": "Medium risk: the message attempts to shame the student publicly.",
    "share_summary": "CyberGuard AI Analysis\nCategory: Harassment\nDanger Level: Medium\nConfidence: 68.1%\nFlagged Words: embarrassing, laughed\nTimestamp: 01 Jul 2026, 12:23 AM\nExplanation: Medium risk: the message attempts to shame the student publicly."
  },
  {
    "id": 7,
    "label": "bullying",
    "scores": {
      "bullying": 0.583,
      "non_bullying": 0.41700000000000004
    },
    "is_bullying": true,
    "timestamp": "2026-06-29T23:23:52.053585",
    "message": "That answer was kind of stupid, but the rest of your work is okay.",
    "category": "insult",
    "category_label": "Insult",
    "danger_level": "Low",
    "confidence": 58.3,
    "danger_score": 58.3,
    "keywords": [
      "stupid"
    ],
    "explanation": "Low risk: the message includes mild insulting language but not sustained bullying.",
    "share_summary": "CyberGuard AI Analysis\nCategory: Insult\nDanger Level: Low\nConfidence: 58.3%\nFlagged Words: stupid\nTimestamp: 29 Jun 2026, 11:23 PM\nExplanation: Low risk: the message includes mild insulting language but not sustained bullying."
  },
  {
    "id": 8,
    "label": "bullying",
    "scores": {
      "bullying": 0.5489999999999999,
      "non_bullying": 0.45100000000000007
    },
    "is_bullying": true,
    "timestamp": "2026-07-05T22:23:52.053585",
    "message": "Let's make a separate group without him for now.",
    "category": "exclusion",
    "category_label": "Exclusion",
    "danger_level": "Low",
    "confidence": 54.9,
    "danger_score": 54.9,
    "keywords": [
      "separate",
      "without"
    ],
    "explanation": "Low risk: the message may signal exclusion, though context could change the interpretation.",
    "share_summary": "CyberGuard AI Analysis\nCategory: Exclusion\nDanger Level: Low\nConfidence: 54.9%\nFlagged Words: separate, without\nTimestamp: 05 Jul 2026, 10:23 PM\nExplanation: Low risk: the message may signal exclusion, though context could change the interpretation."
  },
  {
    "id": 9,
    "label": "non_bullying",
    "scores": {
      "bullying": 0.084,
      "non_bullying": 0.916
    },
    "is_bullying": false,
    "timestamp": "2026-07-04T21:23:52.053585",
    "message": "I disagree with your idea, but thanks for explaining it clearly.",
    "category": "safe",
    "category_label": "Safe",
    "danger_level": "Safe",
    "confidence": 91.6,
    "danger_score": 8.4,
    "keywords": [],
    "explanation": "Safe content: the message disagrees respectfully without bullying indicators.",
    "share_summary": "CyberGuard AI Analysis\nCategory: Safe\nDanger Level: Safe\nConfidence: 91.6%\nFlagged Words: None\nTimestamp: 04 Jul 2026, 09:23 PM\nExplanation: Safe content: the message disagrees respectfully without bullying indicators."
  },
  {
    "id": 10,
    "label": "non_bullying",
    "scores": {
      "bullying": 0.111,
      "non_bullying": 0.889
    },
    "is_bullying": false,
    "timestamp": "2026-07-03T20:23:52.053585",
    "message": "Please stop posting personal comments and keep the discussion respectful.",
    "category": "safe",
    "category_label": "Safe",
    "danger_level": "Safe",
    "confidence": 88.9,
    "danger_score": 11.1,
    "keywords": [],
    "explanation": "Safe content: the message sets a boundary and asks for respectful discussion.",
    "share_summary": "CyberGuard AI Analysis\nCategory: Safe\nDanger Level: Safe\nConfidence: 88.9%\nFlagged Words: None\nTimestamp: 03 Jul 2026, 08:23 PM\nExplanation: Safe content: the message sets a boundary and asks for respectful discussion."
  }
]